vbi_evaluate_blogs/__init__.py
vbi_evaluate_blogs/check_fact_module.py
vbi_evaluate_blogs/check_image_module.py
vbi_evaluate_blogs/check_text_module.py
vbi_evaluate_blogs-0.1.20.dist-info/METADATA
vbi_evaluate_blogs-0.1.20.dist-info/WHEEL
vbi_evaluate_blogs-0.1.20.dist-info/top_level.txt
vbi_evaluate_blogs-0.1.20.dist-info/RECORD
