Metadata-Version: 2.4
Name: vbi-evaluate-blogs
Version: 0.1.20
Summary: A short description of the package
Home-page: https://github.com/lmhung648713/vbi_evaluate_blogs
Author: LeeMinHoon
Author-email: leminhhung19062003@gmail.com
Classifier: Programming Language :: Python :: 3
Classifier: License :: OSI Approved :: MIT License
Classifier: Operating System :: OS Independent
Requires-Python: >=3.7
Requires-Dist: langchain
Requires-Dist: langchain-openai
Requires-Dist: langchain-core
Requires-Dist: langgraph
Requires-Dist: python-dotenv
Requires-Dist: playwright
Requires-Dist: requests
Requires-Dist: typing-extensions
